README.md
setup.py
aoc_common/__init__.py
aoc_common/aoc_commons.py
aoc_commons.egg-info/PKG-INFO
aoc_commons.egg-info/SOURCES.txt
aoc_commons.egg-info/dependency_links.txt
aoc_commons.egg-info/top_level.txt