Metadata-Version: 2.1
Name: aoc-commons
Version: 0.1.2
Summary: A set up of helper functions and classes to assist with Advent of Code problems
Home-page: https://github.com/derailed-dash/Advent-of-Code
Author: derailed-dash
